deep_consultation/__init__.py
deep_consultation/core.py
deep_consultation-0.1.1.dist-info/licenses/LICENSE
deep_consultation-0.1.1.dist-info/METADATA
deep_consultation-0.1.1.dist-info/WHEEL
deep_consultation-0.1.1.dist-info/top_level.txt
deep_consultation-0.1.1.dist-info/RECORD
