Metadata-Version: 2.4
Name: deep-consultation
Version: 0.1.1
Summary: A library for queries with GPTs
Home-page: https://github.com/trucomanx/DeepConsultation
Author: Fernando Pujaico Rivera
Author-email: Fernando Pujaico Rivera <fernando.pujaico.rivera@gmail.com>
Maintainer-email: Fernando Pujaico Rivera <fernando.pujaico.rivera@gmail.com>
License-Expression: GPL-3.0-only WITH Classpath-exception-2.0 OR BSD-3-Clause
Project-URL: Bug Reports, https://github.com/trucomanx/DeepConsultation/issues
Project-URL: Funding, https://trucomanx.github.io/en/funding.html
Project-URL: Source, https://github.com/trucomanx/DeepConsultation
Keywords: writing,AI
Classifier: Programming Language :: Python :: 3
Classifier: Operating System :: OS Independent
Requires-Python: >=3.6
License-File: LICENSE
Requires-Dist: OpenAI
Dynamic: author
Dynamic: home-page
Dynamic: license-file
Dynamic: requires-python
